imdb/__init__.py
imdb/__main__.py
imdb/api.py
imdb/imdb.py
tdm_kevin-0.1.2.dist-info/LICENSE
tdm_kevin-0.1.2.dist-info/METADATA
tdm_kevin-0.1.2.dist-info/WHEEL
tdm_kevin-0.1.2.dist-info/entry_points.txt
tdm_kevin-0.1.2.dist-info/top_level.txt
tdm_kevin-0.1.2.dist-info/RECORD
