Metadata-Version: 2.1
Name: tdm-kevin
Version: 0.1.2
Summary: Run and API to query IMDB movie and tv information.
Author-email: Kevin Amstutz <kamstut@purdue.edu>
License: The MIT License (MIT)        
Keywords: example,imdb,tutorial,fastapi
Classifier: License :: OSI Approved :: MIT License
Classifier: Programming Language :: Python
Classifier: Programming Language :: Python :: 3
Classifier: Framework :: FastAPI
Requires-Python: >=3.10
License-File: LICENSE
Requires-Dist: lxml (>=4.9.1)
Requires-Dist: fastapi (>=0.85.2)
Requires-Dist: Jinja2 (>=3.1.2)
Requires-Dist: uvicorn[standard]
Requires-Dist: requests (>=2.28.1)
